odoo/addons/board_frontdesk/README.rst
odoo/addons/board_frontdesk/__init__.py
odoo/addons/board_frontdesk/__manifest__.py
odoo/addons/board_frontdesk/LICENSE/LICENSE
odoo/addons/board_frontdesk/i18n/board_frontdesk.pot
odoo/addons/board_frontdesk/i18n/br_PT.po
odoo/addons/board_frontdesk/i18n/es.po
odoo/addons/board_frontdesk/i18n/fi.po
odoo/addons/board_frontdesk/i18n/fr_BE.po
odoo/addons/board_frontdesk/i18n/sv.po
odoo/addons/board_frontdesk/static/description/currency.png
odoo/addons/board_frontdesk/static/description/fb.jpg
odoo/addons/board_frontdesk/static/description/icon.png
odoo/addons/board_frontdesk/static/description/in.jpg
odoo/addons/board_frontdesk/static/description/index.html
odoo/addons/board_frontdesk/static/description/insta.jpg
odoo/addons/board_frontdesk/static/description/odooqa32.png
odoo/addons/board_frontdesk/static/description/quickreservation.png
odoo/addons/board_frontdesk/static/description/reservation.png
odoo/addons/board_frontdesk/static/description/romres.png
odoo/addons/board_frontdesk/static/description/roomdetails.png
odoo/addons/board_frontdesk/static/description/todayorder.png
odoo/addons/board_frontdesk/static/description/twitter.jpg
odoo/addons/board_frontdesk/static/description/youtube.jpg
odoo/addons/board_frontdesk/views/board_frontdesk_view.xml
odoo11_addon_board_frontdesk-11.0.1.0.0.dist-info/METADATA
odoo11_addon_board_frontdesk-11.0.1.0.0.dist-info/WHEEL
odoo11_addon_board_frontdesk-11.0.1.0.0.dist-info/top_level.txt
odoo11_addon_board_frontdesk-11.0.1.0.0.dist-info/RECORD
